{
    "inscription_icon": "543a6be681744bb448792692690c4d73ab12dccff2a2372c20d68cb73f825c1ci0",
    "supply": 100,
    "slug": "bitcoin-invaders",
    "description": "In the early days of the Bitcoin blockchain, there were rumors of a powerful and mysterious group known as the 100 Invaders. Many dismissed these rumors as fanciful tales spun by those who had indulged in too many late-night discussions of cryptocurrency. But as the blockchain grew in popularity and value, the whispers of the Invaders grew louder.",
    "source": "magiceden.io",
    "name": "BITCOIN INVADERS "
}